thor_devkit/__init__.py
thor_devkit/abi.py
thor_devkit/block.py
thor_devkit/bloom.py
thor_devkit/certificate.py
thor_devkit/gas.py
thor_devkit/rlp.py
thor_devkit/transaction.py
thor_devkit/cry/__init__.py
thor_devkit/cry/address.py
thor_devkit/cry/blake2b.py
thor_devkit/cry/hdnode.py
thor_devkit/cry/keccak.py
thor_devkit/cry/keystore.py
thor_devkit/cry/mnemonic.py
thor_devkit/cry/secp256k1.py
thor_devkit/cry/utils.py
vechain_thor_devkit-1.1.2.dist-info/LICENSE
vechain_thor_devkit-1.1.2.dist-info/METADATA
vechain_thor_devkit-1.1.2.dist-info/WHEEL
vechain_thor_devkit-1.1.2.dist-info/top_level.txt
vechain_thor_devkit-1.1.2.dist-info/RECORD
